[
    {
        "key": "dbln",
        "value": "%7B%2261556288830733%22%3A%22d2UgBjB5%22%7D",
        "domain": "facebook.com",
        "path": "/login/device-based/",
        "hostOnly": false,
        "creation": "2025-10-12T15:39:32.780Z",
        "lastAccessed": "2025-10-12T15:39:32.780Z"
    },
    {
        "key": "ps_l",
        "value": "1",
        "domain": "facebook.com",
        "path": "/",
        "hostOnly": false,
        "creation": "2025-10-12T15:39:32.780Z",
        "lastAccessed": "2025-10-12T15:39:32.780Z"
    },
    {
        "key": "ps_n",
        "value": "1",
        "domain": "facebook.com",
        "path": "/",
        "hostOnly": false,
        "creation": "2025-10-12T15:39:32.780Z",
        "lastAccessed": "2025-10-12T15:39:32.780Z"
    },
    {
        "key": "sb",
        "value": "8dylaB_d0QEmQFUX57u-_Jn-",
        "domain": "facebook.com",
        "path": "/",
        "hostOnly": false,
        "creation": "2025-10-12T15:39:32.780Z",
        "lastAccessed": "2025-10-12T15:39:32.780Z"
    },
    {
        "key": "vpd",
        "value": "v1%3B768x420x3",
        "domain": "facebook.com",
        "path": "/",
        "hostOnly": false,
        "creation": "2025-10-12T15:39:32.780Z",
        "lastAccessed": "2025-10-12T15:39:32.780Z"
    },
    {
        "key": "pas",
        "value": "61556288830733%3Ak6068lHKvv%2C61556588373385%3Ad8et6GrrBz",
        "domain": "facebook.com",
        "path": "/",
        "hostOnly": false,
        "creation": "2025-10-12T15:39:32.780Z",
        "lastAccessed": "2025-10-12T15:39:32.780Z"
    },
    {
        "key": "wl_cbv",
        "value": "v2%3Bclient_version%3A2927%3Btimestamp%3A1758280677",
        "domain": "facebook.com",
        "path": "/",
        "hostOnly": false,
        "creation": "2025-10-12T15:39:32.780Z",
        "lastAccessed": "2025-10-12T15:39:32.780Z"
    },
    {
        "key": "datr",
        "value": "pBTiaIeePEDC_pAWzWWKdGfE",
        "domain": "facebook.com",
        "path": "/",
        "hostOnly": false,
        "creation": "2025-10-12T15:39:32.780Z",
        "lastAccessed": "2025-10-12T15:39:32.780Z"
    },
    {
        "key": "locale",
        "value": "en_GB",
        "domain": "facebook.com",
        "path": "/",
        "hostOnly": false,
        "creation": "2025-10-12T15:39:32.780Z",
        "lastAccessed": "2025-10-12T15:39:32.780Z"
    },
    {
        "key": "wd",
        "value": "980x1792",
        "domain": "facebook.com",
        "path": "/",
        "hostOnly": false,
        "creation": "2025-10-12T15:39:32.780Z",
        "lastAccessed": "2025-10-12T15:39:32.780Z"
    },
    {
        "key": "c_user",
        "value": "61556288830733",
        "domain": "facebook.com",
        "path": "/",
        "hostOnly": false,
        "creation": "2025-10-12T15:39:32.780Z",
        "lastAccessed": "2025-10-12T15:39:32.780Z"
    },
    {
        "key": "xs",
        "value": "36%3A3pIx13svFR-Miw%3A2%3A1760283566%3A-1%3A-1",
        "domain": "facebook.com",
        "path": "/",
        "hostOnly": false,
        "creation": "2025-10-12T15:39:32.780Z",
        "lastAccessed": "2025-10-12T15:39:32.780Z"
    },
    {
        "key": "fr",
        "value": "1XNzzRnDwFYahT6Bm.AWfyA0QPQ3FqZghDjNobA0D0kM3_0c6CbACxwh5rlKkqjdRGMCQ.Bo65tC..AAA.0.0.Bo68uw.AWdfk6Tq4ssFPG6_V18rMARQkmQ",
        "domain": "facebook.com",
        "path": "/",
        "hostOnly": false,
        "creation": "2025-10-12T15:39:32.780Z",
        "lastAccessed": "2025-10-12T15:39:32.780Z"
    }
]
